dl_coursera_run.py
dl_coursera/Crawler.py
dl_coursera/DLTaskGatherer.py
dl_coursera/Downloader.py
dl_coursera/__init__.py
dl_coursera/define.py
dl_coursera/markup.py
dl_coursera/lib/ExploringTree.py
dl_coursera/lib/MyDict.py
dl_coursera/lib/TaskScheduler.py
dl_coursera/lib/__init__.py
dl_coursera/lib/misc.py
dl_coursera/resource/__init__.py
dl_coursera/resource/bundle.zip
dl_coursera/resource/template/aria2_input_file
dl_coursera/resource/template/curl_input_file
dl_coursera/resource/template/supplement.html
dl_coursera-1.0.1.dist-info/licenses/LICENSE.txt
test/__init__.py
test/test_api.py
test/test_misc.py
dl_coursera-1.0.1.dist-info/METADATA
dl_coursera-1.0.1.dist-info/WHEEL
dl_coursera-1.0.1.dist-info/entry_points.txt
dl_coursera-1.0.1.dist-info/top_level.txt
dl_coursera-1.0.1.dist-info/RECORD
