Metadata-Version: 2.4
Name: dl_coursera
Version: 1.0.1
Summary: A simple, fast, and reliable Coursera crawling & downloading tool
Home-page: https://github.com/FLZ101/dl_coursera
Author: fengleizZZ
Author-email: fenglei4518@hotmail.com
Keywords: dl_coursera,coursera,education,MOOC
Platform: any
Classifier: Development Status :: 4 - Beta
Classifier: Environment :: Console
Classifier: Intended Audience :: End Users/Desktop
Classifier: Programming Language :: Python :: 3 :: Only
Classifier: License :: OSI Approved :: MIT License
Classifier: Operating System :: OS Independent
Classifier: Topic :: Education
Requires-Python: >=3.8
License-File: LICENSE.txt
Requires-Dist: beautifulsoup4>=4.13.4
Requires-Dist: Jinja2>=3.1.6
Requires-Dist: lxml>=6.0.0
Requires-Dist: requests>=2.32.4
Requires-Dist: tqdm>=4.67.1
Provides-Extra: dev
Requires-Dist: black>=24.8.0; extra == "dev"
Dynamic: author
Dynamic: author-email
Dynamic: classifier
Dynamic: description
Dynamic: description-content-type
Dynamic: home-page
Dynamic: keywords
Dynamic: license-file
Dynamic: platform
Dynamic: provides-extra
Dynamic: requires-dist
Dynamic: requires-python
Dynamic: summary
